swtloc/__init__.py
swtloc/abstractions.py
swtloc/base.py
swtloc/configs.py
swtloc/core.py
swtloc/swtlocalizer.py
swtloc/utils.py
swtloc-2.1.1.dist-info/LICENSE
swtloc-2.1.1.dist-info/METADATA
swtloc-2.1.1.dist-info/WHEEL
swtloc-2.1.1.dist-info/top_level.txt
swtloc-2.1.1.dist-info/RECORD
