Metadata-Version: 2.1
Name: swtloc
Version: 2.1.1
Summary: Python Library for Stroke Width Transform
Home-page: https://github.com/ag-ds-bubble/swtloc
Author: Achintya Gupta
Author-email: ag.ds.bubble@gmail.com
License: UNKNOWN
Platform: UNKNOWN
Classifier: Programming Language :: Python :: 3
Classifier: Development Status :: 2 - Pre-Alpha
Classifier: Intended Audience :: Developers
Classifier: Intended Audience :: Education
Classifier: Intended Audience :: Science/Research
Classifier: License :: OSI Approved :: BSD License
Classifier: Operating System :: OS Independent
Classifier: Topic :: Software Development :: Libraries
Requires-Python: >=3.6
License-File: LICENSE
